bizchat/__init__.py
bizchat-6.2.0.dist-info/LICENCE.txt
bizchat-6.2.0.dist-info/METADATA
bizchat-6.2.0.dist-info/WHEEL
bizchat-6.2.0.dist-info/top_level.txt
bizchat-6.2.0.dist-info/RECORD
