Metadata-Version: 2.1
Name: bizchat
Version: 6.2.0
Summary: import this library to use chat from client to  server directly
Home-page: 
Author: mayur
Author-email: mayurdhameliya98@gmai.com
License: MIT
Keywords: server client,chatapp
Platform: UNKNOWN
Classifier: Development Status :: 5 - Production/Stable
Classifier: Intended Audience :: Education
Classifier: Operating System :: Microsoft :: Windows :: Windows 10
Classifier: License :: OSI Approved :: MIT License
Classifier: Programming Language :: Python :: 3
License-File: LICENCE.txt
